anarchy/__init__.py
anarchy/_version.py
anarchy/cohort.py
anarchy/rng.py
anarchy/test.py
anarchy/viz.py
anarchy-1.1.dist-info/METADATA
anarchy-1.1.dist-info/WHEEL
anarchy-1.1.dist-info/top_level.txt
anarchy-1.1.dist-info/RECORD
