Metadata-Version: 2.1
Name: anarchy
Version: 1.1
Summary: Managed chaos for procedural content generation, including incremental/reversible pseudo-random numbers and shuffling/distribution.
Home-page: https://cs.wellesley.edu/~pmwh/anarchy/anarchy/python/doc.html
Author: Peter Mawhorter
Author-email: pmawhorter@gmail.com
License: BSD 3-Clause License
Platform: UNKNOWN
Classifier: Programming Language :: Python :: 3 :: Only
Classifier: License :: OSI Approved :: BSD License
Classifier: Development Status :: 4 - Beta
Classifier: Topic :: Games/Entertainment
Classifier: Topic :: Multimedia
Classifier: Intended Audience :: Developers
Classifier: Operating System :: OS Independent
Classifier: Natural Language :: English
Provides-Extra: test
Requires-Dist: pytest ; extra == 'test'
